synthik/__init__.py
synthik/client.py
synthik/endpoints.py
synthik/http.py
synthik/types.py
synthik_client-0.2.0.dist-info/METADATA
synthik_client-0.2.0.dist-info/WHEEL
synthik_client-0.2.0.dist-info/RECORD
