Metadata-Version: 2.4
Name: synthik-client
Version: 0.2.0
Summary: Python client for Synthik Labs synthetic data generation API
Project-URL: Homepage, https://github.com/Synthik-Labs/synthik-backend
Project-URL: Repository, https://github.com/Synthik-Labs/synthik-backend
Author: Synthik Labs
License: MIT
Requires-Python: >=3.9
Requires-Dist: pydantic>=2.6.0
Requires-Dist: requests>=2.31.0
